abc_graphene_sqlalchemy/__init__.py
abc_graphene_sqlalchemy/converter.py
abc_graphene_sqlalchemy/enums.py
abc_graphene_sqlalchemy/fields.py
abc_graphene_sqlalchemy/interfaces.py
abc_graphene_sqlalchemy/registry.py
abc_graphene_sqlalchemy/types.py
abc_graphene_sqlalchemy/utils.py
abc_graphene_sqlalchemy/tests/__init__.py
abc_graphene_sqlalchemy/tests/conftest.py
abc_graphene_sqlalchemy/tests/models.py
abc_graphene_sqlalchemy/tests/test_converter.py
abc_graphene_sqlalchemy/tests/test_enums.py
abc_graphene_sqlalchemy/tests/test_fields.py
abc_graphene_sqlalchemy/tests/test_interfaces.py
abc_graphene_sqlalchemy/tests/test_query.py
abc_graphene_sqlalchemy/tests/test_query_enums.py
abc_graphene_sqlalchemy/tests/test_reflected.py
abc_graphene_sqlalchemy/tests/test_registry.py
abc_graphene_sqlalchemy/tests/test_schema.py
abc_graphene_sqlalchemy/tests/test_sort_enums.py
abc_graphene_sqlalchemy/tests/test_types.py
abc_graphene_sqlalchemy/tests/test_utils.py
abc_graphene_sqlalchemy-2.2.4.dist-info/LICENSE.md
abc_graphene_sqlalchemy-2.2.4.dist-info/METADATA
abc_graphene_sqlalchemy-2.2.4.dist-info/WHEEL
abc_graphene_sqlalchemy-2.2.4.dist-info/top_level.txt
abc_graphene_sqlalchemy-2.2.4.dist-info/RECORD
