Metadata-Version: 2.1
Name: abc-graphene-sqlalchemy
Version: 2.2.4
Summary: Custom Extension of the original Graphene SQLAlchemy integration
Home-page: https://github.com/maquino1985/graphene-sqlalchemy
Author: Mark Aquino
Author-email: maquino1985@gmail.com
License: MIT
Keywords: api graphql protocol rest relay graphene
Platform: UNKNOWN
Classifier: Development Status :: 3 - Alpha
Classifier: Intended Audience :: Developers
Classifier: Topic :: Software Development :: Libraries
Classifier: Programming Language :: Python :: 2
Classifier: Programming Language :: Python :: 2.7
Classifier: Programming Language :: Python :: 3
Classifier: Programming Language :: Python :: 3.3
Classifier: Programming Language :: Python :: 3.4
Classifier: Programming Language :: Python :: 3.5
Classifier: Programming Language :: Python :: 3.6
Classifier: Programming Language :: Python :: 3.7
Classifier: Programming Language :: Python :: Implementation :: PyPy
Requires-Dist: graphene (<3,>=2.1.3)
Requires-Dist: SQLAlchemy (<2,>=1.1)
Requires-Dist: six (<2,>=1.10.0)
Requires-Dist: singledispatch (<4,>=3.4.0.3)
Provides-Extra: dev
Requires-Dist: tox (==3.7.0) ; extra == 'dev'
Requires-Dist: coveralls (==1.7.0) ; extra == 'dev'
Requires-Dist: pre-commit (==1.14.4) ; extra == 'dev'
Provides-Extra: test
Requires-Dist: pytest (==4.3.1) ; extra == 'test'
Requires-Dist: mock (==2.0.0) ; extra == 'test'
Requires-Dist: pytest-cov (==2.6.1) ; extra == 'test'
Requires-Dist: sqlalchemy-utils (==0.33.9) ; extra == 'test'
